jsonschematomappings/__init__.py
jsonschematomappings-0.0.2.dist-info/LICENSE
jsonschematomappings-0.0.2.dist-info/METADATA
jsonschematomappings-0.0.2.dist-info/WHEEL
jsonschematomappings-0.0.2.dist-info/entry_points.txt
jsonschematomappings-0.0.2.dist-info/top_level.txt
jsonschematomappings-0.0.2.dist-info/RECORD
