Metadata-Version: 2.1
Name: jsonschematomappings
Version: 0.0.2
Summary: Converts JSON schema to OpenSearch/ElasticSearch mappings
Author: William McLaren
Project-URL: Homepage, https://github.com/willmclaren/jsonschematomappings
Project-URL: Bug Tracker, https://github.com/willmclaren/jsonschematomappings/issues
Classifier: Programming Language :: Python :: 3
Classifier: License :: OSI Approved :: GNU General Public License v3 (GPLv3)
Classifier: Operating System :: OS Independent
Requires-Python: >=3.8
License-File: LICENSE
Requires-Dist: setuptools >=65.5.1
Requires-Dist: fastjsonschema <3,>=2.16.2
